logowatch/__init__.py
logowatch/analyzer.py
logowatch/cli.py
logowatch/config.py
logowatch/models.py
logowatch/presets/__init__.py
logowatch/presets/claude-session.yaml
logowatch/presets/docker.yaml
logowatch/presets/mcp.yaml
logowatch-0.5.0.dist-info/licenses/LICENSE
logowatch-0.5.0.dist-info/licenses/NOTICE
logowatch-0.5.0.dist-info/METADATA
logowatch-0.5.0.dist-info/WHEEL
logowatch-0.5.0.dist-info/entry_points.txt
logowatch-0.5.0.dist-info/top_level.txt
logowatch-0.5.0.dist-info/RECORD
