Metadata-Version: 2.4
Name: logowatch
Version: 0.5.0
Summary: Autonomous log analysis tool with configurable pattern rules, incremental detection, and rich output
Author-email: LifeAiTools Team <dev@muid.io>
License: Apache-2.0
Project-URL: Homepage, https://github.com/lifeaitools/logowatch
Project-URL: Documentation, https://github.com/lifeaitools/logowatch#readme
Project-URL: Repository, https://github.com/lifeaitools/logowatch
Project-URL: Issues, https://github.com/lifeaitools/logowatch/issues
Keywords: logs,monitoring,pattern-matching,log-analysis,devops,observability,cli
Classifier: Development Status :: 4 - Beta
Classifier: Environment :: Console
Classifier: Intended Audience :: Developers
Classifier: Intended Audience :: System Administrators
Classifier: License :: OSI Approved :: Apache Software License
Classifier: Operating System :: OS Independent
Classifier: Programming Language :: Python :: 3
Classifier: Programming Language :: Python :: 3.9
Classifier: Programming Language :: Python :: 3.10
Classifier: Programming Language :: Python :: 3.11
Classifier: Programming Language :: Python :: 3.12
Classifier: Topic :: System :: Logging
Classifier: Topic :: System :: Monitoring
Classifier: Topic :: Utilities
Requires-Python: >=3.9
License-File: LICENSE
License-File: NOTICE
Requires-Dist: click>=8.0.0
Requires-Dist: rich>=13.0.0
Requires-Dist: pyyaml>=6.0
Requires-Dist: pydantic>=2.0.0
Provides-Extra: dev
Requires-Dist: pytest>=7.0.0; extra == "dev"
Requires-Dist: pytest-cov>=4.0.0; extra == "dev"
Requires-Dist: black>=23.0.0; extra == "dev"
Requires-Dist: ruff>=0.1.0; extra == "dev"
Requires-Dist: mypy>=1.0.0; extra == "dev"
Dynamic: license-file
